<?xml version="1.0" encoding="UTF-8"?>
<feature
      id="se.gu.featuredashboard.feature"
      label="FeatureDashboard Main Feature"
      version="0.1.0.qualifier"
      provider-name="FeatureDashboard Development Team">

   <copyright>
      Copyright (c) 2019 Chalmers | University of Gothenburg.
   </copyright>

   <requires>
      <import plugin="org.eclipse.core.resources"/>
      <import plugin="org.eclipse.core.jobs" version="3.10.200" match="greaterOrEqual"/>
      <import plugin="org.eclipse.core.runtime"/>
      <import plugin="org.eclipse.ui"/>
      <import plugin="org.eclipse.jface"/>
      <import plugin="org.eclipse.gef.zest.fx"/>
      <import plugin="org.eclipse.gef.zest.fx.ui"/>
      <import plugin="org.eclipse.gef.mvc.fx"/>
      <import plugin="org.eclipse.gef.mvc.fx.ui"/>
      <import plugin="org.eclipse.gef.graph"/>
      <import plugin="org.eclipse.gef.geometry"/>
      <import plugin="org.eclipse.gef.layout"/>
      <import plugin="com.google.guava"/>
      <import plugin="com.google.inject"/>
      <import plugin="org.eclipse.gef.common"/>
      <import plugin="org.eclipse.core.filesystem"/>
      <import plugin="org.eclipse.ui.ide"/>
      <import plugin="org.eclipse.ui.editors"/>
      <import plugin="org.eclipse.e4.core.services"/>
      <import plugin="org.eclipse.ui.workbench"/>
      <import plugin="org.eclipse.jface.text"/>
      <import plugin="org.eclipse.jdt.core"/>
      <import plugin="org.eclipse.cdt.core"/>
      <import plugin="org.eclipse.draw2d"/>
      <import plugin="org.eclipse.nebula.visualization.xygraph"/>
      <import plugin="org.eclipse.nebula.visualization.widgets"/>
      <import plugin="se.gu.featuredashboard.model" version="0.1.0" match="greaterOrEqual"/>
      <import plugin="org.eclipse.core.runtime" version="3.12.0" match="greaterOrEqual"/>
      <import plugin="org.eclipse.capra.core"/>
   </requires>

   <plugin
         id="se.gu.featuredashboard.model"
         download-size="0"
         install-size="0"
         version="0.0.0"
         unpack="false"/>

   <plugin
         id="se.gu.featuredashboard.parsing"
         download-size="0"
         install-size="0"
         version="0.0.0"
         unpack="false"/>

   <plugin
         id="se.gu.featuredashboard.ui"
         download-size="0"
         install-size="0"
         version="0.0.0"
         unpack="false"/>

   <plugin
         id="se.gu.featuredashboard.core"
         download-size="0"
         install-size="0"
         version="0.0.0"
         unpack="false"/>

</feature>
